asda_tools/__init__.py
asda_tools/__main__.py
asda_tools/asdapar2json.py
asda_tools/json2asdapar.py
asda_tools-0.0.2.data/scripts/asdapar2json
asda_tools-0.0.2.dist-info/LICENSE
asda_tools-0.0.2.dist-info/METADATA
asda_tools-0.0.2.dist-info/WHEEL
asda_tools-0.0.2.dist-info/top_level.txt
asda_tools-0.0.2.dist-info/RECORD
