Metadata-Version: 2.1
Name: asda-tools
Version: 0.0.2
Summary: Parser for .par files produced by ASDASoft
Home-page: https://github.com/hadrava/asda_tools
Author: Jan Hadrava
Author-email: had@kam.mff.cuni.cz
License: GPLv2+
Platform: UNKNOWN
Classifier: Programming Language :: Python :: 3
Classifier: License :: OSI Approved :: GNU General Public License v2 or later (GPLv2+)
Classifier: Operating System :: OS Independent
Requires-Python: >=3.4
